[
  {
    "id":"cuerdaIzquierda",
    "clase":"cuerdas",
    "imagen":"./img/objetos/cuerda.png",
    "id_link":""
  },
  {
    "id":"cuerdaDerecha",
    "clase":"cuerdas",
    "imagen":"./img/objetos/cuerda.png",
    "id_link":""
  },
  {
    "id":"btnManejo",
    "clase":"botones",
    "imagen":"./img/botones/manejo_emociones0001.png",
    "id_link":"linkMan"
  },
  {
    "id":"btnActividades",
    "clase":"botones",
    "imagen":"./img/botones/actividades0001.png",
    "id_link":"linkAct"
  },
  {
    "id":"btnImprimibles",
    "clase":"botones",
    "imagen":"./img/botones/imprimir0001.png",
    "id_link":"linkImp"
  }
]
